CodeCryptor/__init__.py
CodeCryptor/__main__.py
CodeCryptor-0.0.1.dist-info/LICENSE
CodeCryptor-0.0.1.dist-info/METADATA
CodeCryptor-0.0.1.dist-info/WHEEL
CodeCryptor-0.0.1.dist-info/entry_points.txt
CodeCryptor-0.0.1.dist-info/top_level.txt
CodeCryptor-0.0.1.dist-info/RECORD
