Metadata-Version: 2.1
Name: CodeCryptor
Version: 0.0.1
Summary: A Python Module for the encryption of code modules
Home-page: https://github.com/KurtCoVayne/CodeCryptor
Author: John Alejandro González
Author-email: johnalejandrog.g4@gmail.com
License: UNKNOWN
Project-URL: Bug Tracker, https://github.com/KurtCoVayne/CodeCryptor
Project-URL: Documentation, https://github.com/KurtCoVayne/CodeCryptor/
Project-URL: Source Code, https://github.com/KurtCoVayne/CodeCryptor
Keywords: encryption crypto decryption python code security
Platform: UNKNOWN
Classifier: License :: OSI Approved :: Python Software Foundation License
Requires-Dist: PyNaCl (>=1.4.0)
